excel_to_json
