Metadata-Version: 1.1
Name: excel-to-json
Version: 1.7
Summary: excel to json
Home-page: http://github.com/wang37921/excel_to_json
Author: Wang Cong
Author-email: wang37921@163.com
License: MIT
Keywords: excel to json
Platform: UNKNOWN
Classifier: Development Status :: 2 - Pre-Alpha
Classifier: License :: OSI Approved :: MIT License
Classifier: Programming Language :: Python :: 3.6
Classifier: Topic :: Text Processing
